near_omni_client/__init__.py
near_omni_client/adapters/__init__.py
near_omni_client/adapters/aave/__init__.py
near_omni_client/adapters/aave/lending_pool.py
near_omni_client/adapters/cctp/__init__.py
near_omni_client/adapters/cctp/attestation_service.py
near_omni_client/adapters/cctp/attestation_service_types.py
near_omni_client/adapters/cctp/fee_service.py
near_omni_client/adapters/cctp/fee_service_types.py
near_omni_client/adapters/cctp/messenger_contract.py
near_omni_client/adapters/cctp/transmitter_contract.py
near_omni_client/adapters/cctp/usdc_contract.py
near_omni_client/chain_signatures/__init__.py
near_omni_client/chain_signatures/constants.py
near_omni_client/chain_signatures/kdf.py
near_omni_client/chain_signatures/segwit_addr.py
near_omni_client/chain_signatures/utils/__init__.py
near_omni_client/chain_signatures/utils/address.py
near_omni_client/crypto/__init__.py
near_omni_client/crypto/keypair.py
near_omni_client/crypto/keypair_base.py
near_omni_client/crypto/keypair_ed25519.py
near_omni_client/crypto/keypair_secp256k1.py
near_omni_client/crypto/public_key.py
near_omni_client/crypto/signature.py
near_omni_client/crypto/types.py
near_omni_client/json_rpc/__init__.py
near_omni_client/json_rpc/access_keys.py
near_omni_client/json_rpc/accounts.py
near_omni_client/json_rpc/block.py
near_omni_client/json_rpc/chunk.py
near_omni_client/json_rpc/gas.py
near_omni_client/json_rpc/network.py
near_omni_client/json_rpc/protocol.py
near_omni_client/json_rpc/transactions.py
near_omni_client/json_rpc/client/__init__.py
near_omni_client/json_rpc/client/near_client.py
near_omni_client/json_rpc/constants/__init__.py
near_omni_client/json_rpc/exceptions/__init__.py
near_omni_client/json_rpc/exceptions/exceptions.py
near_omni_client/json_rpc/exceptions/json_rpc_exception.py
near_omni_client/json_rpc/interfaces/provider.py
near_omni_client/json_rpc/models/__init__.py
near_omni_client/json_rpc/models/access_key_result.py
near_omni_client-0.1.12.dist-info/licenses/LICENSE-APACHE
near_omni_client-0.1.12.dist-info/METADATA
near_omni_client-0.1.12.dist-info/WHEEL
near_omni_client-0.1.12.dist-info/top_level.txt
near_omni_client-0.1.12.dist-info/RECORD
