Metadata-Version: 2.4
Name: near-omni-client
Version: 0.1.12
Summary: Minimal Python library to interact with the NEAR blockchain and Chain Signatures
Requires-Python: >=3.11
License-File: LICENSE-APACHE
Requires-Dist: base58>=2.1.1
Requires-Dist: ecdsa>=0.19.1
Requires-Dist: httpx>=0.28.1
Requires-Dist: loguru>=0.7.3
Requires-Dist: py-near-primitives>=0.2.3
Requires-Dist: pydantic>=2.11.3
Requires-Dist: pynacl>=1.5.0
Requires-Dist: secp256k1>=0.14.0
Requires-Dist: web3>=7.12.1
Provides-Extra: docs
Requires-Dist: furo>=2024.8.6; extra == "docs"
Requires-Dist: myst-parser>=4.0.1; extra == "docs"
Requires-Dist: sphinx>=8.2.3; extra == "docs"
Requires-Dist: sphinx-autobuild>=2024.10.3; extra == "docs"
Requires-Dist: sphinx-autodoc-typehints>=3.1.0; extra == "docs"
Requires-Dist: sphinx-rtd-theme>=3.0.2; extra == "docs"
Requires-Dist: sphinxawesome-theme>=5.3.2; extra == "docs"
Requires-Dist: sphinxcontrib-napoleon>=0.7; extra == "docs"
Dynamic: license-file
